[{
    "schoolId": "8001",
    "organizationNumber": "974568179",
    "organizationNumber360": "974568098",
    "name": "Bamble vgs. avd. Croftholmen",
    "fullName": "Bamble videregående skole, avdeling Croftholmen",
    "shortName": "CROVS",
    "officialName": "Bamble videregående skole",
    "accessGroup": "Elev Bamble vgs",
    "phoneNumber": "35 91 94 00",
    "mail": "bamble.vgs@vtfk.no",
    "address": "Tostrupsvei 7, 3960 Stathelle",
    "geocoded": {
      "lat": "59.04435",
      "lon": "9.70618"
    },
    "yff": true
  },
  {
    "schoolId": "8001",
    "organizationNumber": "974568098",
    "organizationNumber360": "974568098",
    "name": "Bamble vgs. avd. Grasmyr",
    "fullName": "Bamble videregående skole, avdeling Grasmyr",
    "shortName": "BAMVS",
    "officialName": "Bamble videregående skole",
    "accessGroup": "Elev Bamble vgs",
    "phoneNumber": "35 91 94 00",
    "mail": "bamble.vgs@vtfk.no",
    "address": "Tønderveien 6, 3960 Stathelle",
    "geocoded": {
      "lat": "59.02786",
      "lon": "9.70322"
    },
    "yff": true
  },
  {
    "schoolId": "8020",
    "organizationNumber": "974567997",
    "organizationNumber360": "974567997",
    "name": "Bø vgs",
    "fullName": "Bø vidaregåande skule",
    "shortName": "BOEVS",
    "officialName": "Bø vidaregåande skule",
    "accessGroup": "Elev Bø vgs",
    "phoneNumber": "35 91 90 00",
    "mail": "bo.vgs@vtfk.no",
    "address": "Gymnasbakken 23, 3802 Bø",
    "geocoded": {
      "lat": "59.41723",
      "lon": "9.06292"
    },
    "yff": false
  },
  {
    "schoolId": "8050",
    "organizationNumber": "874568082",
    "organizationNumber360": "874568082",
    "name": "Rjukan vgs",
    "fullName": "Rjukan videregående skole",
    "shortName": "RJUVS",
    "officialName": "Rjukan videregående skole",
    "accessGroup": "Elev Rjukan vgs",
    "phoneNumber": "35 91 99 00",
    "mail": "rjukan.vgs@vtfk.no",
    "address": "Såheimveien 22, 3660 Rjukan",
    "geocoded": {
      "lat": "59.87821",
      "lon": "8.58058"
    },
    "yff": true
  },
  {
    "schoolId": "",
    "organizationNumber": "874568112",
    "organizationNumber360": "874568112",
    "name": "Telemark tekniske fagskole",
    "fullName": "Telemark tekniske fagskole",
    "shortName": "Telemark tekniske fagskole",
    "officialName": "Telemark tekniske fagskole",
    "accessGroup": "",
    "phoneNumber": "",
    "mail": "",
    "yff": false
  },
  {
    "schoolId": "8010",
    "organizationNumber": "974568004",
    "organizationNumber360": "974568004",
    "name": "Kragerø vgs",
    "fullName": "Kragerø videregående skole",
    "shortName": "KRAVS",
    "officialName": "Kragerø videregående skole",
    "accessGroup": "Elev Kragerø vgs",
    "phoneNumber": "35 91 95 00",
    "mail": "kragero.vgs@vtfk.no",
    "address": "Frydensborgveien 9-11, 3770 Kragerø",
    "geocoded": {
      "lat": "58.87151",
      "lon": "9.39249"
    },
    "yff": true
  },
  {
    "schoolId": "8022",
    "organizationNumber": "974568012",
    "organizationNumber360": "974568012",
    "name": "Notodden vgs",
    "fullName": "Notodden videregående skole",
    "shortName": "NOTVS",
    "officialName": "Notodden videregående skole",
    "accessGroup": "Elev Notodden vgs",
    "phoneNumber": "35 91 85 00",
    "mail": "notodden.vgs@vtfk.no",
    "address": "Heddalsveien 4, 3674 Notodden",
    "geocoded": {
      "lat": "59.55564",
      "lon": "9.25747"
    },
    "yff": true
  },
  {
    "schoolId": "8006",
    "organizationNumber": "974568020",
    "organizationNumber360": "974568020",
    "name": "Porsgrunn vgs",
    "fullName": "Porsgrunn videregående skole",
    "shortName": "PORVS",
    "officialName": "Porsgrunn videregående skole",
    "accessGroup": "Elev Porsgrunn vgs",
    "phoneNumber": "35 91 75 00",
    "mail": "porsgrunn.vgs@vtfk.no",
    "yff": true
  },
  {
    "schoolId": "8007",
    "organizationNumber": "974568039",
    "organizationNumber360": "974568039",
    "name": "Skien vgs",
    "fullName": "Skien videregående skole",
    "shortName": "SKIVS",
    "officialName": "Skien videregående skole",
    "accessGroup": "Elev Skien vgs",
    "phoneNumber": "35 91 80 00",
    "mail": "skien.vgs@vtfk.no",
    "yff": true
  },
  {
    "schoolId": "8040",
    "organizationNumber": "974568055",
    "organizationNumber360": "974568055",
    "name": "Vest-Telemark vgs. avd. Dalen",
    "fullName": "Vest-Telemark vidaregåande skule, avdeling Dalen",
    "shortName": "DALVS",
    "officialName": "Vest-Telemark vidaregåande skule",
    "accessGroup": "Elev Vest-Telemark vgs",
    "phoneNumber": "35 91 97 00",
    "mail": "vest-telemark.vgs@vtfk.no",
    "address": "Storvegen 195, 3880 Dalen",
    "geocoded": {
      "lat": "59.44657",
      "lon": "7.98785"
    },
    "yff": true
  },
  {
    "schoolId": "8040",
    "organizationNumber": "974568128",
    "organizationNumber360": "974568055",
    "name": "Vest-Telemark vgs. avd. Seljord",
    "fullName": "Vest-Telemark vidaregåande skule, avdeling Seljord",
    "shortName": "SELVS",
    "officialName": "Vest-Telemark vidaregåande skule",
    "accessGroup": "Elev Vest-Telemark vgs",
    "phoneNumber": "35 91 90 70",
    "mail": "vest-telemark.vgs@vtfk.no",
    "address": "Brøløsvegen 2, 3840 Seljord",
    "geocoded": {
      "lat": "59.48254",
      "lon": "8.62049"
    },
    "yff": true
  },
  {
    "schoolId": "8026",
    "organizationNumber": "974568063",
    "organizationNumber360": "974568187",
    "name": "Nome vgs. avd. Lunde",
    "fullName": "Nome videregående skole, avdeling Lunde",
    "shortName": "LUNVS",
    "officialName": "Nome videregående skole",
    "accessGroup": "Elev Nome vgs",
    "phoneNumber": "35 91 88 00",
    "mail": "nome.vgs@vtfk.no",
    "address": "Olav Strannas vei 25, 3825 Lunde",
    "geocoded": {
      "lat": "59.30083",
      "lon": "9.10652"
    },
    "yff": true
  },
  {
    "schoolId": "8004",
    "organizationNumber": "974568071",
    "organizationNumber360": "974568071",
    "name": "Hjalmar Johansen vgs",
    "fullName": "Hjalmar Johansen videregående skole",
    "shortName": "KLOVS",
    "officialName": "Hjalmar Johansen videregående skole",
    "accessGroup": "Elev Hjalmar Johansen vgs",
    "phoneNumber": "35 91 83 00",
    "mail": "hjalmarjohansen.vgs@vtfk.no",
    "yff": true
  },
  {
    "schoolId": "8008",
    "organizationNumber": "974568152",
    "organizationNumber360": "974568152",
    "name": "Skogmo vgs",
    "fullName": "Skogmo videregående skole",
    "shortName": "SKOVS",
    "officialName": "Skogmo videregående skole",
    "accessGroup": "Elev Skogmo vgs",
    "phoneNumber": "35 91 92 00",
    "mail": "skogmo.vgs@vtfk.no",
    "address": "Kjørbekkdalen 11, 3735 Skien",
    "geocoded": {
      "lat": "59.17301",
      "lon": "9.62081"
    },
    "yff": true
  },
  {
    "schoolId": "8026",
    "organizationNumber": "974568187",
    "organizationNumber360": "974568187",
    "name": "Nome vgs. avd. Søve",
    "fullName": "Nome videregående skole, avdeling Søve",
    "shortName": "SOEVS",
    "officialName": "Nome videregående skole",
    "accessGroup": "Elev Nome vgs",
    "phoneNumber": "35 91 87 00",
    "mail": "nome.vgs@vtfk.no",
    "address": "Søveveien 8, 3830 Ulefoss",
    "geocoded": {
      "lat": "59.27845",
      "lon": "9.28459"
    },
    "yff": true
  },
  {
    "schoolId": "8026",
    "organizationNumber": "974568187",
    "organizationNumber360": "974568187",
    "name": "Nome vgs.",
    "fullName": "Nome videregående skole",
    "shortName": "NOMVS",
    "officialName": "Nome videregående skole",
    "accessGroup": "Elev Nome vgs",
    "phoneNumber": "35 91 87 00",
    "mail": "nome.vgs@vtfk.no",
    "address": "Søveveien 8, 3830 Ulefoss",
    "geocoded": {
      "lat": "59.27845",
      "lon": "9.28459"
    },
    "yff": true
  },
  {
    "schoolId": "38032",
    "organizationNumber": "974575086",
    "organizationNumber360": "974575086",
    "name": "Færder vgs",
    "fullName": "Færder videregående skole",
    "shortName": "FRVS",
    "officialName": "Færder videregående skole",
    "accessGroup": "Elev Færder vgs",
    "phoneNumber": "33 30 96 00",
    "mail": "ferder.vgs@vtfk.no",
    "address": "Banebakken 44, 3127 TØNSBERG",
    "geocoded": {
      "lat": "59.26096",
      "lon": "10.41013"
    },
    "yff": false
  },
  {
    "schoolId": "38042",
    "organizationNumber": "974575116",
    "organizationNumber360": "974575116",
    "name": "Sande vgs",
    "fullName": "Sande videregående skole",
    "shortName": "SVS",
    "officialName": "Sande videregående skole",
    "accessGroup": "Elev Sande vgs",
    "phoneNumber": "33 78 50 50",
    "mail": "sande.vgs@vtfk.no",
    "address": "Hans Kristian Evensens vei 53, 3076 SANDE I VESTFOLD",
    "geocoded": {
      "lat": "59.58604",
      "lon": "10.24090"
    },
    "yff": false
  },
  {
    "schoolId": "38050",
    "organizationNumber": "994309153",
    "organizationNumber360": "994309153",
    "name": "Kompetansebyggeren",
    "fullName": "Kompetansebyggeren Vestfold",
    "shortName": "KBV",
    "officialName": "Kompetansebyggeren Vestfold",
    "accessGroup": "Elev Kompetansebyggeren",
    "phoneNumber": "33 30 93 00",
    "mail": "kompetansebyggeren@vtfk.no",
    "address": "Nordbyen 40, 3111 TØNSBERG",
    "geocoded": {
      "lat": "59.27439",
      "lon": "10.39947"
    },
    "yff": false
  },
  {
    "schoolId": "38034",
    "organizationNumber": "974574993",
    "organizationNumber360": "974574993",
    "name": "Greveskogen vgs",
    "fullName": "Greveskogen videregående skole",
    "shortName": "GRVS",
    "officialName": "Greveskogen videregående skole",
    "accessGroup": "Elev Greveskogen vgs",
    "phoneNumber": "33 01 61 00",
    "mail": "greveskogen.vgs@vfk.no",
    "address": "Eikveien 2, 3122 TØNSBERG",
    "geocoded": {
      "lat": "59.28730",
      "lon": "10.41509"
    },
    "yff": false
  },
  {
    "schoolId": "38028",
    "organizationNumber": "974575051",
    "organizationNumber360": "974575051",
    "name": "Melsom vgs",
    "fullName": "Melsom videregående skole",
    "shortName": "MVS",
    "officialName": "Melsom videregående skole",
    "accessGroup": "Elev Melsom vgs",
    "phoneNumber": "33 30 96 00",
    "mail": "melsom.vgs@vtfk.no",
    "address": "Melsomvikveien 180, 3159 MELSOMVIK",
    "geocoded": {
      "lat": "59.23004",
      "lon": "10.34694"
    },
    "yff": false
  },
  {
    "schoolId": "38038",
    "organizationNumber": "874575232",
    "organizationNumber360": "874575232",
    "name": "Re vgs",
    "fullName": "Re videregående skole",
    "shortName": "RVS",
    "officialName": "Re videregående skole",
    "accessGroup": "Elev Re vgs",
    "phoneNumber": "33 30 66 30",
    "mail": "postmottak.revgs@vtfk.no",
    "address": "Bergsåsveien 44, 3175 REVETAL",
    "geocoded": {
      "lat": "59.35799",
      "lon": "10.24879"
    },
    "yff": false
  },
  {
    "schoolId": "38036",
    "organizationNumber": "923261354",
    "organizationNumber360": "923261354",
    "name": "Horten vgs",
    "fullName": "Horten videregående skole",
    "shortName": "HVS",
    "officialName": "Horten videregående skole",
    "accessGroup": "Elev Horten vgs",
    "phoneNumber": "33 07 90 00",
    "mail": "horten.vgs@vtfk.no",
    "address": "Strandpromenaden 33, 3183 HORTEN",
    "geocoded": {
      "lat": "59.42085",
      "lon": "10.48809"
    },
    "yff": false
  },
  {
    "schoolId": "38026",
    "organizationNumber": "974575019",
    "organizationNumber360": "974575019",
    "name": "Sandefjord vgs",
    "fullName": "Sandefjord videregående skole",
    "shortName": "SFVS",
    "officialName": "Sandefjord videregående skole",
    "accessGroup": "Elev Sandefjord vgs",
    "phoneNumber": "33 48 85 00",
    "mail": "sandefjord.vgs@vtfk.no",
    "address": "Krokemoveien 2-4, 3214 SANDEFJORD",
    "geocoded": {
      "lat": "59.13290",
      "lon": "10.20375"
    },
    "yff": false
  },
  {
    "schoolId": "38024",
    "organizationNumber": "974575027",
    "organizationNumber360": "974575027",
    "name": "Thor Heyerdahl vgs",
    "fullName": "Thor Heyerdahl videregående skole",
    "shortName": "THVS",
    "officialName": "Thor Heyerdahl videregående skole",
    "accessGroup": "Elev Thor Heyerdahl vgs",
    "phoneNumber": "33 12 31 00",
    "mail": "thorheyerdahl.vgs@vtfk.no",
    "address": "Hoffsgate 6, 3262 LARVIK",
    "geocoded": {
      "lat": "59.04951",
      "lon": "10.05465"
    },
    "yff": false
  },
  {
    "schoolId": "38036",
    "organizationNumber": "923261354",
    "organizationNumber360": "923261354",
    "name": "Nettskolen Vestfold",
    "fullName": "Nettskolen Vestfold",
    "shortName": "HVS-NETT",
    "officialName": "Nettskolen Vestfold",
    "accessGroup": "Elev Horten vgs",
    "phoneNumber": "33 07 90 00",
    "mail": "nettskolen@vtfk.no",
    "address": "Strandpromenaden 33, 3183 HORTEN",
    "geocoded": {
      "lat": "59.42085",
      "lon": "10.48809"
    },
    "yff": false
  },
  {
    "schoolId": "38040",
    "organizationNumber": "874575062",
    "organizationNumber360": "874575062",
    "name": "Holmestrand vgs",
    "fullName": "Holmestrand videregående skole",
    "shortName": "HLVS",
    "officialName": "Holmestrand videregående skole",
    "accessGroup": "Elev Holmestrand vgs",
    "phoneNumber": "33 06 63 50",
    "mail": "holmestrand.vgs@vtfk.no",
    "address": "Vesthøyveien 7B, 3085 HOLMESTRAND",
    "geocoded": {
      "lat": "59.48239",
      "lon": "10.29552"
    },
    "yff": false
  },
  {
    "schoolId": "38030",
    "organizationNumber": "974575000",
    "organizationNumber360": "974575000",
    "name": "Nøtterøy vgs",
    "fullName": "Nøtterøy videregående skole",
    "shortName": "NVS",
    "officialName": "Nøtterøy videregående skole",
    "accessGroup": "Elev Nøtterøy vgs",
    "phoneNumber": "33 35 10 00",
    "mail": "notteroy.vgs@vtfk.no",
    "address": "Rektorveien 10, 3140 NØTTERØY",
    "geocoded": {
      "lat": "59.11995",
      "lon": "10.19118"
    },
    "yff": false
  }
]